testops/__init__.py
testops/test.py
Thegrandamazingpypublish-0.0.1.dist-info/METADATA
Thegrandamazingpypublish-0.0.1.dist-info/WHEEL
Thegrandamazingpypublish-0.0.1.dist-info/top_level.txt
Thegrandamazingpypublish-0.0.1.dist-info/RECORD
