Metadata-Version: 2.1
Name: Thegrandamazingpypublish
Version: 0.0.1
Summary: basic test
Author: lotan hakli shel ashkelon
Author-email: <ilotanagar@gmail.com>
Keywords: python,sockets
